quizmake/__init__.py
quizmake/__main__.py
quizmake/blank.py
quizmake/core.py
quizmake/corpus.py
quizmake/grammar.py
quizmake/parser.py
quizmake/quizmake.py
quizmake-0.1.6.dist-info/LICENSE
quizmake-0.1.6.dist-info/METADATA
quizmake-0.1.6.dist-info/WHEEL
quizmake-0.1.6.dist-info/top_level.txt
quizmake-0.1.6.dist-info/RECORD
