Metadata-Version: 2.1
Name: quizmake
Version: 0.1.6
Summary: Question generator package for Moodle
Home-page: https://github.com/jnguyen1098/quizmake
Author: jnguyen1098
License: MIT
Keywords: moodle
Platform: UNKNOWN
Classifier: Development Status :: 2 - Pre-Alpha
Classifier: Environment :: Console
Classifier: Intended Audience :: Education
Classifier: Natural Language :: English
Classifier: Operating System :: POSIX
Classifier: Operating System :: Unix
Classifier: Operating System :: Microsoft :: Windows
Classifier: Operating System :: MacOS
Classifier: Programming Language :: Python :: 3
Classifier: Topic :: Education :: Testing
Classifier: License :: OSI Approved :: MIT License
Requires-Python: >=3.7
Requires-Dist: pyparsing
Requires-Dist: wheel
